tools_managed_file/__init__.py
tools_managed_file/duplicate.py
tools_managed_file/exporter.py
tools_managed_file/utils.py
managed_file_py-0.0.1.dist-info/METADATA
managed_file_py-0.0.1.dist-info/WHEEL
managed_file_py-0.0.1.dist-info/entry_points.txt
managed_file_py-0.0.1.dist-info/top_level.txt
managed_file_py-0.0.1.dist-info/RECORD
