Metadata-Version: 2.4
Name: managed-file-py
Version: 0.0.1
Summary: A utility library for managing and processing files.
Author-email: Madamroger <adamsetiadijr07@gmail.com>
Requires-Python: >=3.9
Requires-Dist: pandas
Provides-Extra: dev
Requires-Dist: pytest; extra == "dev"
Requires-Dist: pytest-cov; extra == "dev"
